[
  {
    "id": "0",
    "image": "https://dodopizza.azureedge.net/static/Img/Products/f035c7f46c0844069722f2bb3ee9f113_584x584.jpeg",
    "title": "Пепперони Фреш с перцем",
    "types": [0, 1],
    "sizes": [26, 30, 40],
    "price": 803,
    "category": "Острые",
    "rating": 4,
    "desc": "Пикантная пепперони, увеличенная порция моцареллы, томаты, томатный соус и душистый перец"
  },
  {
    "id": "1",
    "image": "https://dodopizza.azureedge.net/static/Img/Products/Pizza/ru-RU/2ffc31bb-132c-4c99-b894-53f7107a1441.jpg",
    "title": "Сырная",
    "types": [0, 1],
    "sizes": [26, 40],
    "price": 245,
    "category": "Вегетарианская",
    "rating": 6,
    "desc": "Моцарелла, сыры чеддер и пармезан, соус альфредо"
  },
  {
    "id": "2",
    "image": "https://dodopizza.azureedge.net/static/Img/Products/Pizza/ru-RU/6652fec1-04df-49d8-8744-232f1032c44b.jpg",
    "title": "Цыпленок барбекю",
    "types": [0, 1],
    "sizes": [26, 40],
    "price": 295,
    "category": "Мясные",
    "rating": 4,
    "desc": "Цыпленок, бекон, соус барбекю, красный лук, моцарелла, томатный соус"
  },
  {
    "id": "3",
    "image": "https://dodopizza.azureedge.net/static/Img/Products/Pizza/ru-RU/af553bf5-3887-4501-b88e-8f0f55229429.jpg",
    "title": "Кисло-сладкий цыпленок",
    "types": [0, 1],
    "sizes": [26, 30, 40],
    "price": 275,
    "category": "Мясные",
    "rating": 2,
    "desc": "Цыпленок, ананасы, соус карри, красный лук, сладкий перец, моцарелла, томатный соус"
  },
  {
    "id": "4",
    "image": "https://dodopizza.azureedge.net/static/Img/Products/Pizza/ru-RU/b750f576-4a83-48e6-a283-5a8efb68c35d.jpg",
    "title": "Чизбургер-пицца",
    "types": [0, 1],
    "sizes": [26, 30, 40],
    "price": 415,
    "category": "Гриль",
    "rating": 8,
    "desc": "Мясной соус болоньезе, соус бургер, маринованные огурчики, томаты, красный лук, моцарелла"
  },
  {
    "id": "5",
    "image": "https://dodopizza.azureedge.net/static/Img/Products/Pizza/ru-RU/1e1a6e80-b3ba-4a44-b6b9-beae5b1fbf27.jpg",
    "title": "Крэйзи пепперони",
    "types": [0, 1],
    "sizes": [30, 40],
    "price": 580,
    "category": "Острые",
    "rating": 2,
    "desc": "Пикантная пепперони, увеличенная порция моцареллы, томатный соус"
  },
  {
    "id": "6",
    "image": "https://dodopizza.azureedge.net/static/Img/Products/Pizza/ru-RU/d2e337e9-e07a-4199-9cc1-501cc44cb8f8.jpg",
    "title": "Пепперони",
    "types": [0, 1],
    "sizes": [26, 30, 40],
    "price": 675,
    "category": "Мясные",
    "rating": 9,
    "desc": "Пикантная пепперони, увеличенная порция моцареллы, томатный соус"
  },
  {
    "id": "7",
    "image": "https://dodopizza.azureedge.net/static/Img/Products/Pizza/ru-RU/d48003cd-902c-420d-9f28-92d9dc5f73b4.jpg",
    "title": "Маргарита",
    "types": [0, 1],
    "sizes": [26, 30, 40],
    "price": 450,
    "category": "Вегетарианская",
    "rating": 10,
    "desc": "Увеличенная порция моцареллы, томаты, итальянские травы, томатный соус"
  },
  {
    "id": "8",
    "image": "https://dodopizza.azureedge.net/static/Img/Products/Pizza/ru-RU/ec29465e-606b-4a04-a03e-da3940d37e0e.jpg",
    "title": "Четыре сыра",
    "types": [0, 1],
    "sizes": [26, 30, 40],
    "price": 395,
    "category": "Закрытые",
    "rating": 10,
    "desc": "Сыр блю чиз, сыры чеддер и пармезан, моцарелла, соус альфредо"
  },
  {
    "id": "9",
    "image": "https://dodopizza.azureedge.net/static/Img/Products/Pizza/ru-RU/30367198-f3bd-44ed-9314-6f717960da07.jpg",
    "title": "Овощи и грибы 🌱",
    "types": [0, 1],
    "sizes": [26, 30, 40],
    "price": 285,
    "category": "Вегетарианская",
    "rating": 7,
    "desc": "Шампиньоны, томаты, сладкий перец, красный лук, кубики брынзы, моцарелла, томатный соус, итальянские травы"
  },
  {
    "id": "10",
    "image": "https://cdn.dodostatic.net/static/Img/Products/5630c6ed3f394c7ba25e1ef79a67b7ee_584x584.jpeg",
    "title": "Ветчина и сыр",
    "types": [0, 1],
    "sizes": [26, 30, 40],
    "price": 777,
    "category": "Острые",
    "rating": 4,
    "desc": "Ветчина, моцарелла, соус альфредо"
  },
  {
    "id": "11",
    "image": "https://cdn.dodostatic.net/static/Img/Products/b473722281944c78ae1d6532576f92fa_584x584.jpeg",
    "title": "Домашняя",
    "types": [0, 1],
    "sizes": [26, 40],
    "price": 232,
    "category": "Вегетарианская",
    "rating": 6,
    "desc": "Пикантная пепперони, ветчина, маринованные огурчики, томаты, моцарелла, томатный соус"
  },
  {
    "id": "12",
    "image": "https://cdn.dodostatic.net/static/Img/Products/aa845b6e841241fbbff1a770b3ad3103_584x584.jpeg",
    "title": "Ветчина и грибы",
    "types": [0, 1],
    "sizes": [26, 40],
    "price": 277,
    "category": "Мясные",
    "rating": 4,
    "desc": "Ветчина, шампиньоны, увеличенная порция моцареллы, томатный соус"
  },
  {
    "id": "13",
    "image": "https://cdn.dodostatic.net/static/Img/Products/01735d5a70154bd3884899030a671629_584x584.jpeg",
    "title": "Сырный цыпленок",
    "types": [0, 1],
    "sizes": [26, 30, 40],
    "price": 244,
    "category": "Мясные",
    "rating": 2,
    "desc": "Цыпленок, моцарелла, сыры чеддер и пармезан, сырный соус, томаты, соус альфредо, чеснок"
  },
  {
    "id": "14",
    "image": "https://cdn.dodostatic.net/static/Img/Products/af39a1a069eb48e58156bd48b925436e_584x584.jpeg",
    "title": "Овощи гриль",
    "types": [0, 1],
    "sizes": [26, 30, 40],
    "price": 405,
    "category": "Гриль",
    "rating": 8,
    "desc": "Овощи гриль, томаты, красный лук, моцарелла, соус песто, томатный соус, чеснок"
  },
  {
    "id": "15",
    "image": "https://cdn.dodostatic.net/static/Img/Products/d23af75498eb47a8a586313792da917f_584x584.jpeg",
    "title": "Цыпленок ранч",
    "types": [0, 1],
    "sizes": [30, 40],
    "price": 589,
    "category": "Острые",
    "rating": 2,
    "desc": "Цыпленок, ветчина, соус ранч, моцарелла, томаты, чеснок"
  },
  {
    "id": "16",
    "image": "https://cdn.dodostatic.net/static/Img/Products/5bf1c77b3ff44f93bb01c840ab35b033_584x584.jpeg",
    "title": "Гавайская",
    "types": [0, 1],
    "sizes": [26, 30, 40],
    "price": 643,
    "category": "Мясные",
    "rating": 9,
    "desc": "Ветчина, ананасы, моцарелла, томатный соус"
  },
  {
    "id": "17",
    "image": "https://cdn.dodostatic.net/static/Img/Products/17f215303faf4fbc86941e27debee436_584x584.jpeg",
    "title": "Двойная пепперони",
    "types": [0, 1],
    "sizes": [26, 30, 40],
    "price": 419,
    "category": "Мясные",
    "rating": 10,
    "desc": "Двойная порция пикантной пепперони, увеличенная порция моцареллы, томатный соус"
  },
  {
    "id": "18",
    "image": "https://cdn.dodostatic.net/static/Img/Products/f34008b8a9b94097b0cf81a632bb766c_584x584.jpeg",
    "title": "Цыпленок карри",
    "types": [0, 1],
    "sizes": [26, 30, 40],
    "price": 355,
    "category": "Закрытые",
    "rating": 10,
    "desc": "Цыпленок, ананасы, соус карри, красный лук, сладкий перец, моцарелла, томатный соус"
  },
  {
    "id": "19",
    "image": "https://cdn.dodostatic.net/static/Img/Products/02270e55a3204ccaaf26d75f0c817d28_584x584.jpeg",
    "title": "Белая пепперони",
    "types": [0, 1],
    "sizes": [26, 30, 40],
    "price": 270,
    "category": "Мясные",
    "rating": 7,
    "desc": "Пикантная пепперони, соус альфредо, моцарелла"
  }
]
